id_translation/__init__.py
id_translation/_tasks/__init__.py
id_translation/_tasks/_base_task.py
id_translation/_tasks/_map.py
id_translation/_tasks/_names.py
id_translation/_tasks/_translate.py
id_translation/_translator.py
id_translation/_utils/debug_logging_formatter.py
id_translation/_uuid_utils.py
id_translation/dio/__init__.py
id_translation/dio/_data_structure_io.py
id_translation/dio/_resolve.py
id_translation/dio/default/__init__.py
id_translation/dio/default/_dict.py
id_translation/dio/default/_sequence.py
id_translation/dio/default/_set.py
id_translation/dio/default/_single_value.py
id_translation/dio/exceptions.py
id_translation/dio/integration/__init__.py
id_translation/dio/integration/dask.py
id_translation/dio/integration/pandas.py
id_translation/dio/integration/polars.py
id_translation/exceptions.py
id_translation/fetching/__init__.py
id_translation/fetching/_abstract_fetcher.py
id_translation/fetching/_cache_access.py
id_translation/fetching/_fetcher.py
id_translation/fetching/_memory_fetcher.py
id_translation/fetching/_multi_fetcher.py
id_translation/fetching/_pandas_fetcher.py
id_translation/fetching/_sql_fetcher.py
id_translation/fetching/exceptions.py
id_translation/fetching/types.py
id_translation/logging.py
id_translation/mapping/__init__.py
id_translation/mapping/_cardinality.py
id_translation/mapping/_directional_mapping.py
id_translation/mapping/_heuristic_score.py
id_translation/mapping/_mapper.py
id_translation/mapping/exceptions.py
id_translation/mapping/filter_functions.py
id_translation/mapping/heuristic_functions.py
id_translation/mapping/matrix/__init__.py
id_translation/mapping/matrix/_score_helper.py
id_translation/mapping/matrix/_score_matrix.py
id_translation/mapping/score_functions.py
id_translation/mapping/types.py
id_translation/offline/__init__.py
id_translation/offline/_format.py
id_translation/offline/_format_applier.py
id_translation/offline/_magic_dict.py
id_translation/offline/_translation_map.py
id_translation-1.0.4.dist-info/METADATA
id_translation-1.0.4.dist-info/WHEEL
id_translation-1.0.4.dist-info/entry_points.txt
id_translation-1.0.4.dist-info/licenses/LICENSE.md
id_translation-1.0.4.dist-info/RECORD
