Metadata-Version: 2.4
Name: id-translation
Version: 1.0.4
Summary: Convert IDs into human-readable labels.
License: MIT
License-File: LICENSE.md
Keywords: id-translation
Author: Richard Sundqvist
Author-email: richard.sundqvist@live.se
Requires-Python: >=3.11
Classifier: Development Status :: 5 - Production/Stable
Classifier: Intended Audience :: Developers
Classifier: Intended Audience :: Science/Research
Classifier: Operating System :: POSIX :: Linux
Classifier: Operating System :: MacOS
Classifier: Operating System :: Microsoft :: Windows
Classifier: License :: OSI Approved :: MIT License
Classifier: Natural Language :: English
Classifier: Typing :: Typed
Classifier: Programming Language :: Python :: 3
Classifier: Programming Language :: Python :: 3 :: Only
Classifier: Programming Language :: Python :: 3.11
Classifier: Programming Language :: Python :: 3.12
Classifier: Programming Language :: Python :: 3.13
Classifier: Programming Language :: Python :: 3.14
Provides-Extra: fetching
Requires-Dist: pandas (>=2.0.3) ; extra == "fetching"
Requires-Dist: rics (>=5.1.0)
Requires-Dist: sqlalchemy (>=2.0.5) ; extra == "fetching"
Project-URL: Bug Tracker, https://github.com/rsundqvist/id-translation/issues
Project-URL: Changelog, https://github.com/rsundqvist/id-translation/blob/master/CHANGELOG.md
Project-URL: Documentation, https://id-translation.readthedocs.io
Project-URL: Homepage, https://github.com/rsundqvist/id-translation
Project-URL: Repository, https://github.com/rsundqvist/id-translation
